normcst/__init__.py
normcst/black.py
normcst/utils.py
normcst-0.2.0.dist-info/licenses/LICENSE
normcst-0.2.0.dist-info/METADATA
normcst-0.2.0.dist-info/WHEEL
normcst-0.2.0.dist-info/top_level.txt
normcst-0.2.0.dist-info/RECORD
