Metadata-Version: 2.4
Name: normcst
Version: 0.2.0
Summary: Tools for LibCST related to normalization.
Author-email: Andreas Rappold <not_evil@rappold1.at>
License: MIT License
Project-URL: Homepage, https://gitlab.com/notEvil/normcst
Project-URL: Bug Tracker, https://gitlab.com/notEvil/normcst/-/issues
Requires-Python: >=3.9
License-File: LICENSE
Requires-Dist: libcst
Provides-Extra: black
Requires-Dist: black; extra == "black"
Provides-Extra: test
Requires-Dist: black; extra == "test"
Requires-Dist: pytest; extra == "test"
Provides-Extra: all
Requires-Dist: black; extra == "all"
Requires-Dist: pytest; extra == "all"
Dynamic: license-file
